socassess/__init__.py
socassess/ai/__init__.py
socassess/ai/ai.py
socassess/ai/config.py
socassess/config.py
socassess/console.py
socassess/create.py
socassess/display.py
socassess/email/__init__.py
socassess/email/config.py
socassess/email/email.py
socassess/email/expert.py
socassess/exception.py
socassess/feedback.py
socassess/feedback_helper.py
socassess/level.py
socassess/parse_args.py
socassess/socassess.template.toml
socassess/userargs.py
socassess-0.3.0.dist-info/LICENSE
socassess-0.3.0.dist-info/METADATA
socassess-0.3.0.dist-info/WHEEL
socassess-0.3.0.dist-info/entry_points.txt
socassess-0.3.0.dist-info/RECORD
