Metadata-Version: 2.1
Name: socassess
Version: 0.3.0
Summary: make test-based assessment's feedback easy to setup
Home-page: https://github.com/h365chen/socassess
Keywords: automated,feedback,education
Author: Huanyi Chen
Author-email: huanyi.chen@uwaterloo.ca
Requires-Python: >=3.9,<4.0
Classifier: Programming Language :: Python :: 3
Classifier: Programming Language :: Python :: 3.9
Classifier: Programming Language :: Python :: 3.10
Classifier: Programming Language :: Python :: 3.11
Classifier: Programming Language :: Python :: 3.12
Classifier: Topic :: Education
Classifier: Topic :: Education :: Testing
Classifier: Topic :: Software Development :: Testing
Requires-Dist: colorama (>=0.4.6,<0.5.0)
Requires-Dist: numpy (>=1.26.0,<2.0.0)
Requires-Dist: openai (>=1.13.3,<2.0.0)
Requires-Dist: pytest (>=7.4.1,<8.0.0)
Requires-Dist: pytest-dependency (>=0.5.1,<0.6.0)
Requires-Dist: pytest-order (>=1.1.0,<2.0.0)
Requires-Dist: pytest-timeout (>=2.1.0,<3.0.0)
Requires-Dist: tomli (>=2.0.1,<3.0.0) ; python_version >= "3.9" and python_version < "3.11"
Requires-Dist: xmltodict (>=0.13.0,<0.14.0)
Project-URL: Repository, https://github.com/h365chen/socassess
